vultest/__init__.py
vultest/vultest.py
vultest-0.1.2.dist-info/LICENSE
vultest-0.1.2.dist-info/METADATA
vultest-0.1.2.dist-info/WHEEL
vultest-0.1.2.dist-info/top_level.txt
vultest-0.1.2.dist-info/RECORD
