Metadata-Version: 2.1
Name: vultest
Version: 0.1.2
Summary: Vultest is a python library for testing router vulnerability.
Home-page: https://github.com/Fa1sal-ali/vultest
Author: Faisal Ali
Author-email: fzl.ali33@gmail.com
License: MIT
Platform: Linux; MacOS X; Windows
Requires-Python: >=3.8
Requires-Dist: ipaddress (==1.0.23)
Requires-Dist: paramiko (==2.6.0)
